ctd/__init__.py
ctd/_version.py
ctd/extras.py
ctd/plotting.py
ctd/processing.py
ctd/read.py
ctd-1.4.7.dist-info/LICENSE.txt
ctd-1.4.7.dist-info/METADATA
ctd-1.4.7.dist-info/WHEEL
ctd-1.4.7.dist-info/top_level.txt
ctd-1.4.7.dist-info/RECORD
