Metadata-Version: 2.2
Name: ctd
Version: 1.4.7
Summary: Tools to load hydrographic data into pandas DataFrame
Author-email: Filipe Fernandes <ocefpaf+ctd@gmail.com>
License: BSD-3-Clause
Project-URL: documentation, https://pyoceans.github.io/python-ctd
Project-URL: homepage, https://github.com/pyoceans/python-ctd
Project-URL: repository, https://github.com/pyoceans/python-ctd
Classifier: Programming Language :: Python :: 3 :: Only
Classifier: Programming Language :: Python :: 3.11
Classifier: Programming Language :: Python :: 3.12
Classifier: Programming Language :: Python :: 3.13
Requires-Python: >=3.11
License-File: LICENSE.txt
Requires-Dist: chardet
Requires-Dist: gsw>=3.3.0
Requires-Dist: matplotlib
Requires-Dist: numpy>=2
Requires-Dist: pandas>=0.24.0
Requires-Dist: pandas-flavor>=0.1.2
Requires-Dist: scipy
